<annotation>
	<folder>labeled2</folder>
	<filename>1-9_1-9.x1000.y4000.jpg</filename>
	<path>C:\Users\Indira\Desktop\友達-SMT_and_FPC\New folder\labeled2\1-9_1-9.x1000.y4000.jpg</path>
	<source>
		<database>Unknown</database>
	</source>
	<size>
		<width>1000</width>
		<height>999</height>
		<depth>1</depth>
	</size>
	<segmented>0</segmented>
	<object>
		<name>Etching</name>
		<pose>Unspecified</pose>
		<truncated>0</truncated>
		<difficult>0</difficult>
		<bndbox>
			<xmin>804</xmin>
			<ymin>634</ymin>
			<xmax>931</xmax>
			<ymax>710</ymax>
		</bndbox>
	</object>
	<object>
		<name>Etching</name>
		<pose>Unspecified</pose>
		<truncated>0</truncated>
		<difficult>0</difficult>
		<bndbox>
			<xmin>823</xmin>
			<ymin>855</ymin>
			<xmax>921</xmax>
			<ymax>961</ymax>
		</bndbox>
	</object>
	<object>
		<name>Etching</name>
		<pose>Unspecified</pose>
		<truncated>0</truncated>
		<difficult>0</difficult>
		<bndbox>
			<xmin>869</xmin>
			<ymin>715</ymin>
			<xmax>931</xmax>
			<ymax>807</ymax>
		</bndbox>
	</object>
</annotation>
