<annotation>
	<folder>labeled2</folder>
	<filename>1-9_1-9.x10000.y2000.jpg</filename>
	<path>C:\Users\Indira\Desktop\友達-SMT_and_FPC\New folder\labeled2\1-9_1-9.x10000.y2000.jpg</path>
	<source>
		<database>Unknown</database>
	</source>
	<size>
		<width>1000</width>
		<height>1000</height>
		<depth>1</depth>
	</size>
	<segmented>0</segmented>
	<object>
		<name>Pinhole</name>
		<pose>Unspecified</pose>
		<truncated>0</truncated>
		<difficult>0</difficult>
		<bndbox>
			<xmin>140</xmin>
			<ymin>763</ymin>
			<xmax>186</xmax>
			<ymax>821</ymax>
		</bndbox>
	</object>
	<object>
		<name>Scar</name>
		<pose>Unspecified</pose>
		<truncated>0</truncated>
		<difficult>0</difficult>
		<bndbox>
			<xmin>264</xmin>
			<ymin>773</ymin>
			<xmax>363</xmax>
			<ymax>816</ymax>
		</bndbox>
	</object>
	<object>
		<name>Scar</name>
		<pose>Unspecified</pose>
		<truncated>0</truncated>
		<difficult>0</difficult>
		<bndbox>
			<xmin>406</xmin>
			<ymin>752</ymin>
			<xmax>498</xmax>
			<ymax>798</ymax>
		</bndbox>
	</object>
	<object>
		<name>Discolor</name>
		<pose>Unspecified</pose>
		<truncated>0</truncated>
		<difficult>0</difficult>
		<bndbox>
			<xmin>659</xmin>
			<ymin>766</ymin>
			<xmax>752</xmax>
			<ymax>983</ymax>
		</bndbox>
	</object>
	<object>
		<name>Discolor</name>
		<pose>Unspecified</pose>
		<truncated>1</truncated>
		<difficult>0</difficult>
		<bndbox>
			<xmin>927</xmin>
			<ymin>728</ymin>
			<xmax>1000</xmax>
			<ymax>995</ymax>
		</bndbox>
	</object>
	<object>
		<name>Discolor</name>
		<pose>Unspecified</pose>
		<truncated>0</truncated>
		<difficult>0</difficult>
		<bndbox>
			<xmin>657</xmin>
			<ymin>500</ymin>
			<xmax>748</xmax>
			<ymax>762</ymax>
		</bndbox>
	</object>
	<object>
		<name>Discolor</name>
		<pose>Unspecified</pose>
		<truncated>0</truncated>
		<difficult>0</difficult>
		<bndbox>
			<xmin>927</xmin>
			<ymin>412</ymin>
			<xmax>995</xmax>
			<ymax>708</ymax>
		</bndbox>
	</object>
</annotation>
